lunasync/__about__.py
lunasync/__init__.py
lunasync/__main__.py
lunasync/cli.py
lunasync/config.py
lunasync/main.py
lunasync/savedata.py
lunasync/data/default_config.csv
lunasync-0.1.4.dist-info/METADATA
lunasync-0.1.4.dist-info/RECORD
lunasync-0.1.4.dist-info/WHEEL
lunasync-0.1.4.dist-info/entry_points.txt
lunasync-0.1.4.dist-info/top_level.txt
