Metadata-Version: 2.1
Name: lunasync
Version: 0.1.4
Summary: Keep downloaded booru searches up-to-date, similar to Danbooru subscriptions.
Home-page: https://github.com/mirukan/lunasync
Author: miruka
Author-email: miruka@disroot.org
License: LGPLv3
Keywords: lunakit lunafind booru danbooru api image ugoira anime cli terminal scrap saved tag search filter download sync subscription cron
Platform: UNKNOWN
Classifier: Development Status :: 3 - Alpha
Classifier: Intended Audience :: End Users/Desktop
Classifier: Environment :: Console
Classifier: Topic :: Utilities
Classifier: Topic :: Internet :: WWW/HTTP :: Indexing/Search
Classifier: License :: OSI Approved :: GNU Lesser General Public License v3 or later (LGPLv3+)
Classifier: Programming Language :: Python :: 3
Classifier: Programming Language :: Python :: 3 :: Only
Classifier: Programming Language :: Python :: 3.6
Classifier: Programming Language :: Python :: 3.7
Classifier: Natural Language :: English
Classifier: Operating System :: POSIX
Classifier: Operating System :: Microsoft :: Windows
Requires-Python: >=3.6, <4
Requires-Dist: appdirs
Requires-Dist: atomicfile
Requires-Dist: docopt
Requires-Dist: lunafind (<0.6.0,>=0.5.4)
Requires-Dist: setuptools
